[
    {
        "Title": "Project 1",
        "Description": "Description1",
        "Image": "Image1",
        "DeployedLink": "DeployedLink1",
        "Github": "Github"
    },
    {
        "Title": "Project 2",
        "Description": "Description2",
        "Image": "Image2",
        "DeployedLink": "DeployedLink2",
        "Github": "Github"
    },
    {
        "Title": "Project 3",
        "Description": "Description3",
        "Image": "Image3",
        "DeployedLink": "DeployedLink3",
        "Github": "Github"
    },
    {
        "Title": "Project 4",
        "Description": "Description4",
        "Image": "Image4",
        "DeployedLink": "DeployedLink4",
        "Github": "Github"
    },
    {
        "Title": "Project 5",
        "Description": "Description5",
        "Image": "Image5",
        "DeployedLink": "DeployedLink5",
        "Github": "Github"
    },
    {
        "Title": "Project 6",
        "Description": "Description6",
        "Image": "Image6",
        "DeployedLink": "DeployedLink6",
        "Github": "Github"
    }
]